[
  {
    "trip_date": "2026-02-20",
    "region": "Los Angeles",
    "landing": "Marina Del Rey Sportfishing",
    "boat": "New Del Mar",
    "trip_type": "1/2 Day Twilight",
    "anglers": 43,
    "fish_counts": "8 Calico Bass, 10 Sand Bass, 205 Sculpin",
    "total_fish": 223
  },
  {
    "trip_date": "2026-02-20",
    "region": "Los Angeles",
    "landing": "Marina Del Rey Sportfishing",
    "boat": "Spitfire",
    "trip_type": "3/4 Day",
    "anglers": 14,
    "fish_counts": "2 Calico Bass, 8 Sand Bass, 70 Sculpin",
    "total_fish": 80
  },
  {
    "trip_date": "2026-02-20",
    "region": "Orange County",
    "landing": "Dana Wharf Sportfishing",
    "boat": "Clemente",
    "trip_type": "3/4 Day",
    "anglers": 8,
    "fish_counts": "1 Calico Bass, 4 Halibut, 1 Sand Bass",
    "total_fish": 6
  },
  {
    "trip_date": "2026-02-20",
    "region": "Orange County",
    "landing": "Dana Wharf Sportfishing",
    "boat": "Dana Pride",
    "trip_type": "1/2 Day AM",
    "anglers": 15,
    "fish_counts": "2 Calico Bass, 12 Calico Bass Released, 4 Halibut, 8 Sand Bass, 13 Sculpin",
    "total_fish": 39
  },
  {
    "trip_date": "2026-02-20",
    "region": "Orange County",
    "landing": "Newport Landing",
    "boat": "Patriot (Newport)",
    "trip_type": "1/2 Day PM",
    "anglers": 14,
    "fish_counts": "3 Calico Bass, 12 Sculpin, 70 Whitefish",
    "total_fish": 85
  },
  {
    "trip_date": "2026-02-20",
    "region": "San Diego",
    "landing": "Fisherman's Landing",
    "boat": "Dolphin",
    "trip_type": "1/2 Day PM",
    "anglers": 47,
    "fish_counts": "6 Sand Bass, 36 Sculpin",
    "total_fish": 42
  },
  {
    "trip_date": "2026-02-20",
    "region": "San Diego",
    "landing": "Oceanside Sea Center",
    "boat": "Chubasco II",
    "trip_type": "1/2 Day Twilight",
    "anglers": 14,
    "fish_counts": "14 Calico Bass, 30 Calico Bass Released, 15 Sand Bass, 12 Sculpin",
    "total_fish": 71
  },
  {
    "trip_date": "2026-02-20",
    "region": "San Diego",
    "landing": "Oceanside Sea Center",
    "boat": "Southern Cal",
    "trip_type": "1/2 Day AM",
    "anglers": 12,
    "fish_counts": "36 Sculpin",
    "total_fish": 36
  }
]