[
  {
    "trip_date": "2025-09-30",
    "region": "Los Angeles",
    "landing": "Long Beach Sportfishing",
    "boat": "El Patron",
    "trip_type": "Full Day",
    "anglers": 9,
    "fish_counts": "Santa Catalina Island 16 Barracuda, 1 Yellowtail, 27 Calico Bass, 12 Bonito, 51 Rockfish",
    "total_fish": 91
  },
  {
    "trip_date": "2025-09-30",
    "region": "Los Angeles",
    "landing": "Long Beach Sportfishing",
    "boat": "Victory",
    "trip_type": "3/4 Day",
    "anglers": 26,
    "fish_counts": "Local 43 Salmon Grouper, 1 Cabezon, 50 Sculpin, 33 Sheephead, 27 Calico Bass, 57 Whitefish, 40 Rockfish, 15 Vermillion Rockfish",
    "total_fish": 207
  },
  {
    "trip_date": "2025-09-30",
    "region": "Los Angeles",
    "landing": "Marina Del Rey Sportfishing",
    "boat": "Betty-O",
    "trip_type": "3/4 Day",
    "anglers": 4,
    "fish_counts": "40 Rockfish",
    "total_fish": 40
  },
  {
    "trip_date": "2025-09-30",
    "region": "Los Angeles",
    "landing": "Marina Del Rey Sportfishing",
    "boat": "New Del Mar",
    "trip_type": "1/2 Day AM",
    "anglers": 39,
    "fish_counts": "8 Sand Bass, 168 Sculpin, 1 Lingcod, 107 Rockfish",
    "total_fish": 284
  },
  {
    "trip_date": "2025-09-30",
    "region": "Orange County",
    "landing": "Dana Wharf Sportfishing",
    "boat": "Clemente",
    "trip_type": "1/2 Day AM",
    "anglers": 45,
    "fish_counts": "4 Sand Bass, 1 Halibut, 4 Sculpin, 5 Bonito, 7 Rockfish, 16 Sand Bass Released , 28 Calico Bass Released",
    "total_fish": 49
  },
  {
    "trip_date": "2025-09-30",
    "region": "Orange County",
    "landing": "Dana Wharf Sportfishing",
    "boat": "Fury",
    "trip_type": "2 Day",
    "anglers": 23,
    "fish_counts": "9 Bluefin Tuna, 5 Barracuda, 3 Sheephead, 9 Yellowtail, 3 Dorado, 208 Whitefish, 195 Rockfish, 2 Yellowfin Tuna",
    "total_fish": 431
  },
  {
    "trip_date": "2025-09-30",
    "region": "Orange County",
    "landing": "Dana Wharf Sportfishing",
    "boat": "Sum Fun",
    "trip_type": "3/4 Day",
    "anglers": 30,
    "fish_counts": "20 Sculpin, 15 Whitefish, 180 Rockfish",
    "total_fish": 215
  },
  {
    "trip_date": "2025-09-30",
    "region": "Orange County",
    "landing": "Davey's Locker",
    "boat": "Blackfish",
    "trip_type": "Full Day",
    "anglers": 6,
    "fish_counts": "1 Bluefin Tuna, 30 Calico Bass, 60 Rockfish",
    "total_fish": 91
  },
  {
    "trip_date": "2025-09-30",
    "region": "Orange County",
    "landing": "Davey's Locker",
    "boat": "Western Pride",
    "trip_type": "1/2 Day AM",
    "anglers": 30,
    "fish_counts": "1 Sand Bass, 150 Sculpin, 12 Whitefish, 55 Rockfish, 60 Vermilion Rockfish",
    "total_fish": 218
  },
  {
    "trip_date": "2025-09-30",
    "region": "Orange County",
    "landing": "Newport Landing",
    "boat": "Patriot (Newport)",
    "trip_type": "3/4 Day",
    "anglers": 25,
    "fish_counts": "7 Calico Bass, 45 Bonito",
    "total_fish": 52
  },
  {
    "trip_date": "2025-09-30",
    "region": "San Diego",
    "landing": "Fisherman's Landing",
    "boat": "Dolphin",
    "trip_type": "1/2 Day AM",
    "anglers": 11,
    "fish_counts": "3 Sculpin, 22 Rockfish",
    "total_fish": 25
  },
  {
    "trip_date": "2025-09-30",
    "region": "San Diego",
    "landing": "Fisherman's Landing",
    "boat": "Dolphin",
    "trip_type": "1/2 Day PM",
    "anglers": 21,
    "fish_counts": "2 Sand Bass, 13 Sculpin, 10 Sheephead, 5 Calico Bass, 126 Rockfish",
    "total_fish": 156
  },
  {
    "trip_date": "2025-09-30",
    "region": "San Diego",
    "landing": "Fisherman's Landing",
    "boat": "Liberty",
    "trip_type": "2 Day",
    "anglers": 18,
    "fish_counts": "44 Bluefin Tuna, 4 Yellowfin Tuna",
    "total_fish": 48
  },
  {
    "trip_date": "2025-09-30",
    "region": "San Diego",
    "landing": "Fisherman's Landing",
    "boat": "Tomahawk",
    "trip_type": "2 Day",
    "anglers": 27,
    "fish_counts": "108 Bluefin Tuna, 1 Yellowfin Tuna",
    "total_fish": 109
  },
  {
    "trip_date": "2025-09-30",
    "region": "San Diego",
    "landing": "Fisherman's Landing",
    "boat": "Tradition",
    "trip_type": "1.5 Day",
    "anglers": 15,
    "fish_counts": "30 Bluefin Tuna, 7 Yellowtail, 4 Dorado, 5 Yellowfin Tuna",
    "total_fish": 42
  },
  {
    "trip_date": "2025-09-30",
    "region": "San Diego",
    "landing": "H&M Landing",
    "boat": "Alicia",
    "trip_type": "1/2 Day Twilight",
    "anglers": 10,
    "fish_counts": "26 Spiny Lobster, 18 Rock Crab, 56 Spiny Lobster Released",
    "total_fish": 0
  },
  {
    "trip_date": "2025-09-30",
    "region": "San Diego",
    "landing": "H&M Landing",
    "boat": "Grande",
    "trip_type": "Overnight",
    "anglers": 14,
    "fish_counts": "24 Bluefin Tuna",
    "total_fish": 24
  },
  {
    "trip_date": "2025-09-30",
    "region": "San Diego",
    "landing": "H&M Landing",
    "boat": "Old Glory",
    "trip_type": "1.5 Day",
    "anglers": 29,
    "fish_counts": "58 Bluefin Tuna, 3 Dorado, 1 Yellowfin Tuna",
    "total_fish": 59
  },
  {
    "trip_date": "2025-09-30",
    "region": "San Diego",
    "landing": "Oceanside Sea Center",
    "boat": "Southern Cal",
    "trip_type": "1/2 Day AM",
    "anglers": 5,
    "fish_counts": "15 Sculpin, 25 Bonito, 15 Rockfish",
    "total_fish": 55
  },
  {
    "trip_date": "2025-09-30",
    "region": "San Diego",
    "landing": "Point Loma Sportfishing",
    "boat": "Daily Double",
    "trip_type": "1/2 Day AM",
    "anglers": 13,
    "fish_counts": "61 Sculpin, 12 Rockfish",
    "total_fish": 73
  },
  {
    "trip_date": "2025-09-30",
    "region": "San Diego",
    "landing": "Seaforth Sportfishing",
    "boat": "Highliner",
    "trip_type": "2 Day",
    "anglers": 17,
    "fish_counts": "68 Bluefin Tuna, 3 Yellowfin Tuna",
    "total_fish": 71
  },
  {
    "trip_date": "2025-09-30",
    "region": "San Diego",
    "landing": "Seaforth Sportfishing",
    "boat": "New Seaforth",
    "trip_type": "1/2 Day AM",
    "anglers": 20,
    "fish_counts": "1 Sand Bass, 1 Sheephead, 1 Calico Bass, 15 Whitefish, 88 Rockfish",
    "total_fish": 106
  },
  {
    "trip_date": "2025-09-30",
    "region": "San Diego",
    "landing": "Seaforth Sportfishing",
    "boat": "New Seaforth",
    "trip_type": "1/2 Day PM",
    "anglers": 18,
    "fish_counts": "3 Sheephead, 23 Whitefish, 2 Bonito, 35 Rockfish",
    "total_fish": 63
  },
  {
    "trip_date": "2025-09-30",
    "region": "San Diego",
    "landing": "Seaforth Sportfishing",
    "boat": "Pacifica",
    "trip_type": "1.5 Day",
    "anglers": 28,
    "fish_counts": "50 Bluefin Tuna, 5 Yellowtail, 8 Yellowfin Tuna",
    "total_fish": 63
  },
  {
    "trip_date": "2025-09-30",
    "region": "San Diego",
    "landing": "Seaforth Sportfishing",
    "boat": "Polaris Supreme",
    "trip_type": "3 Day",
    "anglers": 24,
    "fish_counts": "144 Bluefin Tuna (up to 200 pounds), 60 Yellowtail, 10 Dorado, 96 Yellowfin Tuna",
    "total_fish": 156
  },
  {
    "trip_date": "2025-09-30",
    "region": "San Diego",
    "landing": "Seaforth Sportfishing",
    "boat": "San Diego",
    "trip_type": "Full Day Offshore",
    "anglers": 35,
    "fish_counts": "",
    "total_fish": 0
  },
  {
    "trip_date": "2025-09-30",
    "region": "San Diego",
    "landing": "Seaforth Sportfishing",
    "boat": "Voyager",
    "trip_type": "1.5 Day",
    "anglers": 14,
    "fish_counts": "28 Bluefin Tuna, 16 Yellowtail, 5 Dorado, 10 Skipjack Tuna, 2 Yellowfin Tuna",
    "total_fish": 46
  },
  {
    "trip_date": "2025-09-30",
    "region": "Santa Barbara",
    "landing": "Santa Barbara Landing",
    "boat": "Coral Sea",
    "trip_type": "3/4 Day",
    "anglers": 24,
    "fish_counts": "48 Lingcod, 240 Whitefish, 192 Rockfish",
    "total_fish": 480
  },
  {
    "trip_date": "2025-09-30",
    "region": "Santa Barbara",
    "landing": "Santa Barbara Landing",
    "boat": "Stardust",
    "trip_type": "3/4 Day",
    "anglers": 18,
    "fish_counts": "1 Cabezon, 2 Sheephead, 36 Lingcod, 130 Whitefish, 179 Rockfish",
    "total_fish": 347
  },
  {
    "trip_date": "2025-09-30",
    "region": "SoCal",
    "landing": "Patriot Sportfishing",
    "boat": "Patriot (Avila Beach)",
    "trip_type": "1/2 Day AM",
    "anglers": 10,
    "fish_counts": "Out Front 2 Bocaccio, 3 Copper Rockfish, 2 Lingcod, 88 Rockcod, 1 Red Rockcod",
    "total_fish": 2
  },
  {
    "trip_date": "2025-09-30",
    "region": "SoCal",
    "landing": "Patriot Sportfishing",
    "boat": "Sunny Day",
    "trip_type": "1/2 Day AM",
    "anglers": 2,
    "fish_counts": "Pecho Rock 2 Bocaccio, 3 Copper Rockfish, 2 Lingcod, 88 Rockcod, 1 Red Rockcod",
    "total_fish": 2
  },
  {
    "trip_date": "2025-09-30",
    "region": "Ventura",
    "landing": "Channel Islands Sportfishing",
    "boat": "Aloha Spirit Old",
    "trip_type": "Full Day",
    "anglers": 11,
    "fish_counts": "12 Halibut, 1 Sculpin, 1 Sheephead, 5 Calico Bass, 6 Lingcod, 110 Rockfish",
    "total_fish": 135
  },
  {
    "trip_date": "2025-09-30",
    "region": "Ventura",
    "landing": "Channel Islands Sportfishing",
    "boat": "Speed Twin",
    "trip_type": "1/2 Day AM",
    "anglers": 9,
    "fish_counts": "4 Sand Bass, 1 Halibut, 17 Calico Bass, 2 Lingcod, 13 Whitefish, 90 Rockfish",
    "total_fish": 127
  },
  {
    "trip_date": "2025-09-30",
    "region": "Ventura",
    "landing": "Ventura Harbor Sportfishing",
    "boat": "Pacific Eagle",
    "trip_type": "Full Day",
    "anglers": 14,
    "fish_counts": "1 Sculpin, 2 Sheephead, 1 Calico Bass, 6 Lingcod, 67 Whitefish, 103 Rockfish",
    "total_fish": 180
  }
]