[
  {
    "trip_date": "2025-10-21",
    "region": "Los Angeles",
    "landing": "22nd Street Landing",
    "boat": "Amigo",
    "trip_type": "1.5 Day",
    "anglers": 14,
    "fish_counts": "28 Bluefin Tuna, 1 Sheephead, 9 Yellowtail, 12 Bonito, 61 Rockfish, 28 Red Snapper",
    "total_fish": 111
  },
  {
    "trip_date": "2025-10-21",
    "region": "Los Angeles",
    "landing": "Long Beach Sportfishing",
    "boat": "Victory",
    "trip_type": "3/4 Day",
    "anglers": 14,
    "fish_counts": "Local 2 Sand Bass, 5 Salmon Grouper, 1 Sculpin, 24 Sheephead, 140 Whitefish, 68 Rockfish, 10 Vermillion Rockfish",
    "total_fish": 235
  },
  {
    "trip_date": "2025-10-21",
    "region": "Los Angeles",
    "landing": "Marina Del Rey Sportfishing",
    "boat": "New Del Mar",
    "trip_type": "1/2 Day AM",
    "anglers": 36,
    "fish_counts": "12 Sand Bass, 170 Sculpin, 5 Sheephead, 3 Calico Bass",
    "total_fish": 190
  },
  {
    "trip_date": "2025-10-21",
    "region": "Orange County",
    "landing": "Dana Wharf Sportfishing",
    "boat": "Clemente",
    "trip_type": "3/4 Day",
    "anglers": 20,
    "fish_counts": "1 Sand Bass, 3 Sculpin, 13 Whitefish, 87 Rockfish, 8 Sanddab",
    "total_fish": 104
  },
  {
    "trip_date": "2025-10-21",
    "region": "Orange County",
    "landing": "Dana Wharf Sportfishing",
    "boat": "Fury",
    "trip_type": "Overnight",
    "anglers": 14,
    "fish_counts": "7 Sheephead, 1 Yellowtail, 70 Calico Bass, 18 Whitefish, 44 Bonito, 100 Calico Bass Released",
    "total_fish": 240
  },
  {
    "trip_date": "2025-10-21",
    "region": "Orange County",
    "landing": "Dana Wharf Sportfishing",
    "boat": "Reel Fun",
    "trip_type": "1/2 Day AM",
    "anglers": 32,
    "fish_counts": "1 Sand Bass, 1 Sculpin, 9 Sheephead, 30 Sand Bass Released",
    "total_fish": 11
  },
  {
    "trip_date": "2025-10-21",
    "region": "Orange County",
    "landing": "Dana Wharf Sportfishing",
    "boat": "Sum Fun",
    "trip_type": "3/4 Day",
    "anglers": 40,
    "fish_counts": "18 Sculpin, 8 Whitefish, 200 Rockfish",
    "total_fish": 226
  },
  {
    "trip_date": "2025-10-21",
    "region": "Orange County",
    "landing": "Davey's Locker",
    "boat": "Freelance",
    "trip_type": "3/4 Day",
    "anglers": 61,
    "fish_counts": "240 Sculpin, 2 Sheephead, 215 Whitefish, 50 Rockfish",
    "total_fish": 507
  },
  {
    "trip_date": "2025-10-21",
    "region": "San Diego",
    "landing": "Fisherman's Landing",
    "boat": "Dolphin",
    "trip_type": "1/2 Day AM",
    "anglers": 17,
    "fish_counts": "126 Rockfish",
    "total_fish": 126
  },
  {
    "trip_date": "2025-10-21",
    "region": "San Diego",
    "landing": "Fisherman's Landing",
    "boat": "Dolphin",
    "trip_type": "1/2 Day PM",
    "anglers": 17,
    "fish_counts": "10 Sand Bass, 100 Sculpin, 1 Calico Bass",
    "total_fish": 111
  },
  {
    "trip_date": "2025-10-21",
    "region": "San Diego",
    "landing": "H&M Landing",
    "boat": "Alicia",
    "trip_type": "1/2 Day Twilight",
    "anglers": 10,
    "fish_counts": "17 Spiny Lobster, 3 Rock Crab, 27 Spiny Lobster Released",
    "total_fish": 0
  },
  {
    "trip_date": "2025-10-21",
    "region": "San Diego",
    "landing": "H&M Landing",
    "boat": "Legend",
    "trip_type": "1.5 Day",
    "anglers": 26,
    "fish_counts": "52 Bluefin Tuna",
    "total_fish": 52
  },
  {
    "trip_date": "2025-10-21",
    "region": "San Diego",
    "landing": "H&M Landing",
    "boat": "Premier",
    "trip_type": "1/2 Day PM",
    "anglers": 23,
    "fish_counts": "1 Sand Bass, 10 Sculpin, 7 Whitefish, 20 Sanddab",
    "total_fish": 18
  },
  {
    "trip_date": "2025-10-21",
    "region": "San Diego",
    "landing": "Oceanside Sea Center",
    "boat": "Southern Cal",
    "trip_type": "1/2 Day AM",
    "anglers": 14,
    "fish_counts": "80 Rockfish",
    "total_fish": 80
  },
  {
    "trip_date": "2025-10-21",
    "region": "San Diego",
    "landing": "Seaforth Sportfishing",
    "boat": "El Gato Dos",
    "trip_type": "Full Day Offshore",
    "anglers": 3,
    "fish_counts": "6 Bluefin Tuna",
    "total_fish": 6
  },
  {
    "trip_date": "2025-10-21",
    "region": "San Diego",
    "landing": "Seaforth Sportfishing",
    "boat": "Highliner",
    "trip_type": "1.5 Day",
    "anglers": 26,
    "fish_counts": "43 Bluefin Tuna, 100 Rockfish, 52 Vermilion Rockfish",
    "total_fish": 143
  },
  {
    "trip_date": "2025-10-21",
    "region": "San Diego",
    "landing": "Seaforth Sportfishing",
    "boat": "New Seaforth",
    "trip_type": "1/2 Day AM",
    "anglers": 15,
    "fish_counts": "150 Rockfish",
    "total_fish": 150
  },
  {
    "trip_date": "2025-10-21",
    "region": "San Diego",
    "landing": "Seaforth Sportfishing",
    "boat": "San Diego",
    "trip_type": "Full Day Offshore",
    "anglers": 34,
    "fish_counts": "",
    "total_fish": 0
  },
  {
    "trip_date": "2025-10-21",
    "region": "San Diego",
    "landing": "Seaforth Sportfishing",
    "boat": "Voyager",
    "trip_type": "2 Day",
    "anglers": 9,
    "fish_counts": "36 Bluefin Tuna",
    "total_fish": 36
  },
  {
    "trip_date": "2025-10-21",
    "region": "Ventura",
    "landing": "Channel Islands Sportfishing",
    "boat": "Aloha Spirit Old",
    "trip_type": "Full Day",
    "anglers": 11,
    "fish_counts": "1 Halibut, 17 Calico Bass, 4 Lingcod, 4 Whitefish, 4 Bonito, 67 Rockfish",
    "total_fish": 97
  },
  {
    "trip_date": "2025-10-21",
    "region": "Ventura",
    "landing": "Channel Islands Sportfishing",
    "boat": "Speed Twin",
    "trip_type": "1/2 Day AM",
    "anglers": 14,
    "fish_counts": "18 Lingcod, 140 Rockfish",
    "total_fish": 158
  }
]