[
  {
    "trip_date": "2025-05-15",
    "region": "Los Angeles",
    "landing": "22nd Street Landing",
    "boat": "Ghost",
    "trip_type": "Overnight",
    "anglers": 8,
    "fish_counts": "29 Calico Bass, 4 Halibut",
    "total_fish": 33
  },
  {
    "trip_date": "2025-05-15",
    "region": "Los Angeles",
    "landing": "22nd Street Landing",
    "boat": "Monte Carlo",
    "trip_type": "1/2 Day AM",
    "anglers": 32,
    "fish_counts": "46 Rockfish, 160 Sculpin, 7 Whitefish",
    "total_fish": 213
  },
  {
    "trip_date": "2025-05-15",
    "region": "Los Angeles",
    "landing": "Marina Del Rey Sportfishing",
    "boat": "Betty-O",
    "trip_type": "3/4 Day",
    "anglers": 5,
    "fish_counts": "1 Lingcod, 40 Rockfish",
    "total_fish": 41
  },
  {
    "trip_date": "2025-05-15",
    "region": "Los Angeles",
    "landing": "Marina Del Rey Sportfishing",
    "boat": "Spitfire",
    "trip_type": "3/4 Day",
    "anglers": 20,
    "fish_counts": "8 Halibut, 105 Rockfish, 1 Sheephead",
    "total_fish": 114
  },
  {
    "trip_date": "2025-05-15",
    "region": "Los Angeles",
    "landing": "Redondo Beach Sportfishing",
    "boat": "Redondo Special",
    "trip_type": "1/2 Day PM",
    "anglers": 14,
    "fish_counts": "79 Rockfish, 4 Whitefish",
    "total_fish": 83
  },
  {
    "trip_date": "2025-05-15",
    "region": "Orange County",
    "landing": "Dana Wharf Sportfishing",
    "boat": "Clemente",
    "trip_type": "3/4 Day",
    "anglers": 25,
    "fish_counts": "28 Calico Bass, 45 Rockfish, 15 Sculpin, 2 Sheephead, 11 Whitefish",
    "total_fish": 101
  },
  {
    "trip_date": "2025-05-15",
    "region": "Orange County",
    "landing": "Dana Wharf Sportfishing",
    "boat": "Dana Pride",
    "trip_type": "1/2 Day AM",
    "anglers": 47,
    "fish_counts": "6 Calico Bass, 60 Calico Bass Released, 4 Sand Bass, 3 Sculpin, 6 Sheephead, 4 Whitefish",
    "total_fish": 83
  },
  {
    "trip_date": "2025-05-15",
    "region": "Orange County",
    "landing": "Dana Wharf Sportfishing",
    "boat": "Sum Fun",
    "trip_type": "3/4 Day",
    "anglers": 21,
    "fish_counts": "210 Rockfish",
    "total_fish": 210
  },
  {
    "trip_date": "2025-05-15",
    "region": "Orange County",
    "landing": "Davey's Locker",
    "boat": "Blackfish",
    "trip_type": "1/2 Day AM",
    "anglers": 6,
    "fish_counts": "60 Rockfish",
    "total_fish": 60
  },
  {
    "trip_date": "2025-05-15",
    "region": "Orange County",
    "landing": "Davey's Locker",
    "boat": "Western Pride",
    "trip_type": "1/2 Day PM",
    "anglers": 26,
    "fish_counts": "90 Rockfish, 130 Sculpin, 3 Whitefish",
    "total_fish": 223
  },
  {
    "trip_date": "2025-05-15",
    "region": "Orange County",
    "landing": "Newport Landing",
    "boat": "Thunderbird",
    "trip_type": "Overnight",
    "anglers": 30,
    "fish_counts": "1 Barracuda, 4 Bonito, 7 Calico Bass, 73 Rockfish, 18 Sheephead, 139 Whitefish",
    "total_fish": 242
  },
  {
    "trip_date": "2025-05-15",
    "region": "San Diego",
    "landing": "Fisherman's Landing",
    "boat": "Dolphin",
    "trip_type": "1/2 Day AM",
    "anglers": 29,
    "fish_counts": "276 Rockfish",
    "total_fish": 276
  },
  {
    "trip_date": "2025-05-15",
    "region": "San Diego",
    "landing": "Fisherman's Landing",
    "boat": "Dolphin",
    "trip_type": "1/2 Day PM",
    "anglers": 18,
    "fish_counts": "3 Lingcod, 59 Rockfish, 1 Sculpin, 5 Sheephead",
    "total_fish": 68
  },
  {
    "trip_date": "2025-05-15",
    "region": "San Diego",
    "landing": "Fisherman's Landing",
    "boat": "Liberty",
    "trip_type": "3/4 Day",
    "anglers": 14,
    "fish_counts": "70 Bonito, 43 Rockfish",
    "total_fish": 113
  },
  {
    "trip_date": "2025-05-15",
    "region": "San Diego",
    "landing": "H&M Landing",
    "boat": "Premier",
    "trip_type": "1/2 Day AM",
    "anglers": 19,
    "fish_counts": "142 Rockfish",
    "total_fish": 142
  },
  {
    "trip_date": "2025-05-15",
    "region": "San Diego",
    "landing": "Oceanside Sea Center",
    "boat": "Southern Cal",
    "trip_type": "1/2 Day AM",
    "anglers": 10,
    "fish_counts": "80 Rockfish",
    "total_fish": 80
  },
  {
    "trip_date": "2025-05-15",
    "region": "San Diego",
    "landing": "Seaforth Sportfishing",
    "boat": "New Seaforth",
    "trip_type": "1/2 Day AM",
    "anglers": 22,
    "fish_counts": "160 Rockfish",
    "total_fish": 160
  },
  {
    "trip_date": "2025-05-15",
    "region": "San Diego",
    "landing": "Seaforth Sportfishing",
    "boat": "New Seaforth",
    "trip_type": "1/2 Day PM",
    "anglers": 23,
    "fish_counts": "34 Calico Bass, 75 Calico Bass Released, 1 Sheephead, 1 Yellowtail",
    "total_fish": 111
  },
  {
    "trip_date": "2025-05-15",
    "region": "San Luis Obispo",
    "landing": "Virg's Landing",
    "boat": "Rita G",
    "trip_type": "3/4 Day",
    "anglers": 14,
    "fish_counts": "112 Rockfish",
    "total_fish": 112
  },
  {
    "trip_date": "2025-05-15",
    "region": "Santa Barbara",
    "landing": "Santa Barbara Landing",
    "boat": "Stardust",
    "trip_type": "3/4 Day",
    "anglers": 15,
    "fish_counts": "14 Lingcod, 117 Rockfish, 1 Sheephead, 2 Whitefish",
    "total_fish": 134
  },
  {
    "trip_date": "2025-05-15",
    "region": "Ventura",
    "landing": "Channel Islands Sportfishing",
    "boat": "Aloha Spirit Old",
    "trip_type": "Full Day",
    "anglers": 12,
    "fish_counts": "5 Halibut, 24 Lingcod, 8 Rockfish, 1 Whitefish",
    "total_fish": 38
  },
  {
    "trip_date": "2025-05-15",
    "region": "Ventura",
    "landing": "Channel Islands Sportfishing",
    "boat": "Cobra",
    "trip_type": "Full Day",
    "anglers": 2,
    "fish_counts": "18 Whitefish",
    "total_fish": 18
  },
  {
    "trip_date": "2025-05-15",
    "region": "Ventura",
    "landing": "Channel Islands Sportfishing",
    "boat": "Gentleman",
    "trip_type": "3/4 Day",
    "anglers": 27,
    "fish_counts": "1 Barracuda, 1 Calico Bass, 11 Halibut, 5 Sand Bass",
    "total_fish": 18
  },
  {
    "trip_date": "2025-05-15",
    "region": "Ventura",
    "landing": "Channel Islands Sportfishing",
    "boat": "Graylight",
    "trip_type": "Full Day",
    "anglers": 6,
    "fish_counts": "8 Calico Bass, 3 Halibut, 1 Rockfish, 3 Whitefish",
    "total_fish": 15
  },
  {
    "trip_date": "2025-05-15",
    "region": "Ventura",
    "landing": "Channel Islands Sportfishing",
    "boat": "Mirage",
    "trip_type": "Overnight",
    "anglers": 21,
    "fish_counts": "1 Barracuda, 2 Halibut, 7 Lingcod, 77 Rockfish, 4 Whitefish",
    "total_fish": 91
  },
  {
    "trip_date": "2025-05-15",
    "region": "Ventura",
    "landing": "Channel Islands Sportfishing",
    "boat": "Speed Twin",
    "trip_type": "1/2 Day AM",
    "anglers": 22,
    "fish_counts": "3 Halibut, 2 Lingcod, 171 Rockfish, 41 Whitefish",
    "total_fish": 217
  },
  {
    "trip_date": "2025-05-15",
    "region": "Ventura",
    "landing": "Pierpoint Landing",
    "boat": "Enterprise",
    "trip_type": "3/4 Day",
    "anglers": 23,
    "fish_counts": "230 Rockfish",
    "total_fish": 230
  },
  {
    "trip_date": "2025-05-15",
    "region": "Ventura",
    "landing": "Ventura Harbor Sportfishing",
    "boat": "Endeavor (Ventura)",
    "trip_type": "Overnight",
    "anglers": 19,
    "fish_counts": "6 Lingcod, 55 Rockfish, 9 Sheephead, 19 Whitefish",
    "total_fish": 89
  }
]